utilitarian_collector/__init__.py
utilitarian_collector/exceptions.py
utilitarian_collector/handlers.py
utilitarian_collector/management.py
utilitarian_collector/request_handlers.py
utilitarian_collector/servers.py
utilitarian_collector/conf/__init__.py
utilitarian_collector/conf/global_settings.py
utilitarian_collector/managers/__init__.py
utilitarian_collector/managers/dlms.py
utilitarian_collector/utils/__init__.py
utilitarian_collector/utils/log.py
utilitarian_collector/utils/module_loading.py
utilitarian_collector-0.0.2.dist-info/DESCRIPTION.rst
utilitarian_collector-0.0.2.dist-info/LICENSE.txt
utilitarian_collector-0.0.2.dist-info/METADATA
utilitarian_collector-0.0.2.dist-info/RECORD
utilitarian_collector-0.0.2.dist-info/WHEEL
utilitarian_collector-0.0.2.dist-info/entry_points.txt
utilitarian_collector-0.0.2.dist-info/metadata.json
utilitarian_collector-0.0.2.dist-info/top_level.txt
