Metadata-Version: 2.0
Name: utilitarian-collector
Version: 0.0.2
Summary: Server to receive and handle meter data in an extensible way
Home-page: https://github.com/pwitab/utilitarian-collector
Author: Henrik Palmlund Wahlgren @ Palmlund Wahlgren Innovative Technology AB
Author-email: henrik@pwit.se
License: BSD-3
Platform: UNKNOWN
Classifier: Development Status :: 3 - Alpha
Classifier: License :: OSI Approved :: BSD License
Classifier: Natural Language :: English
Classifier: Programming Language :: Python
Classifier: Programming Language :: Python :: 3
Classifier: Programming Language :: Python :: 3 :: Only
Classifier: Programming Language :: Python :: 3.6
Classifier: Topic :: Software Development :: Libraries
Requires-Python: >=3.6
